CodeCraftOJ/__init__.py
CodeCraftOJ/assets/blank.3141643e.js
CodeCraftOJ/assets/blank.ec23ec6e.css
CodeCraftOJ/assets/index.1ca9452f.css
CodeCraftOJ/assets/index.33fd1eba.js
CodeCraftOJ/assets/index.5d9b4289.js
CodeCraftOJ/assets/index.a0561d2f.css
CodeCraftOJ/assets/vendor.814c45db.js
CodeCraftOJ/assets/vendor.aa3cb504.css
CodeCraftOJ/cli.py
CodeCraftOJ/favicon.ico
CodeCraftOJ/index.html
CodeCraftOJ/server/interface.py
CodeCraftOJ/server/responses.py
CodeCraftOJ/server/serve.py
CodeCraftOJ/server/utils.py
codecraftoj-0.2.0.dist-info/entry_points.txt
codecraftoj-0.2.0.dist-info/WHEEL
codecraftoj-0.2.0.dist-info/METADATA
codecraftoj-0.2.0.dist-info/RECORD
