Metadata-Version: 2.1
Name: codecraftoj
Version: 0.2.0
Summary: 
Author: InEase
Author-email: InEase28@gmail.com
Requires-Python: >=3.8,<4.0
Classifier: Programming Language :: Python :: 3
Classifier: Programming Language :: Python :: 3.10
Classifier: Programming Language :: Python :: 3.8
Classifier: Programming Language :: Python :: 3.9
Requires-Dist: Flask (>=2.0.3,<3.0.0)
